port_range/__init__.py
port_range/tests/__init__.py
port_range/tests/test_port_range.py
port_range-2.2.0.dist-info/LICENSE
port_range-2.2.0.dist-info/METADATA
port_range-2.2.0.dist-info/WHEEL
port_range-2.2.0.dist-info/entry_points.txt
port_range-2.2.0.dist-info/top_level.txt
port_range-2.2.0.dist-info/RECORD
